    {
      "apiVersion": "2015-05-01-preview",
      "name": "loadBalancer",
      "type": "Microsoft.Network/loadBalancers",
      "location": "[resourceGroup().location]",
      "dependsOn": [
        "Microsoft.Network/publicIPAddresses/publicIp"
      ],
      "properties": {
        "frontendIPConfigurations": [
          {
            "name": "LBFE",
            "properties": {
              "publicIPAddress": {
                "id": "[resourceId('Microsoft.Network/publicIPAddresses','publicIp')]"
              }
            }
          }
        ],
        "backendAddressPools": [
          {
            "name": "LBBAP"
          }
        ],
        "inboundNatRules": [
          {
            "name": "rdp-vm",
            "properties": {
              "frontendIPConfiguration": {
                "id": "[concat(resourceId('Microsoft.Network/loadBalancers','loadBalancer'),'/frontendIPConfigurations/LBFE')]"
              },
              "protocol": "tcp",
              "frontendPort": 3389,
              "backendPort": 3389,
              "enableFloatingIP": false
            }
          }
        ]
      }
    },